Workbook

Sheet LC Tracker
A1: LETTER OF CREDIT TRACKER — 2026
A2: 2026# | B2: Customer | C2: Country | D2: Customer # | E2: Advising Bank | F2: Advising Bank # | G2: Payment Term | H2: Issuing Bank2 | I2: Issuing Bank #2 | J2: Issuance Date | K2: Expiry Date | L2: Latest Date O/S | M2: Sight / Deferred | N2: CCY | O2: LC Value (USD) | P2: Inv Number | Q2: Value | R2: Pres. Date | S2: Status | T2: Coll. Date | U2: Due Date | V2: Tracking # | W2: Inv Number2 | X2: Value3 | Y2: Pres. Date4 | Z2: Status5 | AA2: Coll. Date6 | AB2: Due Date7 | AC2: Tracking #8 | AD2: Inv Number9 | AE2: Value10 | AF2: Pres. Date11 | AG2: Status12 | AH2: Coll. Date13 | AI2: Due Date14 | AJ2: Tracking #15 | AK2: Inv Number16 | AL2: Value17 | AM2: Pres. Date18 | AN2: Status19 | AO2: Coll. Date20 | AP2: Due Date21 | AQ2: Tracking #22 | AR2: Inv Number23 | AS2: Value24 | AT2: Pres. Date25 | AU2: Status26 | AV2: Coll. Date27 | AW2: Due Date28 | AX2: Tracking #29 | AY2: Inv Number30 | AZ2: Value31 | BA2: Pres. Date32 | BB2: Status33 | BC2: Coll. Date34 | BD2: Due Date35 | BE2: Tracking #36 | BF2: Inv Number37 | BG2: Value38 | BH2: Pres. Date39 | BI2: Status40 | BJ2: Coll. Date41 | BK2: Due Date42 | BL2: Tracking #43 | BM2: Inv Number44 | BN2: Value45 | BO2: Pres. Date46 | BP2: Status47 | BQ2: Coll. Date48 | BR2: Due Date49 | BS2: Tracking #50 | BT2: Inv Number51 | BU2: Value52 | BV2: Pres. Date53 | BW2: Status54 | BX2: Coll. Date55 | BY2: Due Date56 | BZ2: Tracking #57 | CA2: Inv Number58 | CB2: Value59 | CC2: Pres. Date60 | CD2: Status61 | CE2: Coll. Date62 | CF2: Due Date63 | CG2: Tracking #64 | CH2: Inv Number65 | CI2: Value66 | CJ2: Pres. Date67 | CK2: Status68 | CL2: Coll. Date69 | CM2: Due Date70 | CN2: Tracking #71 | CO2: Inv Number72 | CP2: Value73 | CQ2: Pres. Date74 | CR2: Status75 | CS2: Coll. Date76 | CT2: Due Date77 | CU2: Tracking #78 | CV2: Total Presented | CW2: Total
A3: 1 | B3: Al Hashar Pharmacy Llc | C3: =_xlfn.XLOOKUP(Table1[[#This Row],[Customer]], 'Cust Data'!D:D, 'Cust Data'!E:E, "N/A") -> Oman | D3: =_xlfn.XLOOKUP(Table1[[#This Row],[Customer]], 'Cust Data'!D:D, 'Cust Data'!C:C, "N/A") -> 2000006 | E3: BANK MUSCAT SA | F3: 2026/ILC/3378 | G3: 180 Days From TCN | H3: BANK MUSCAT OMAN | I3: 26/BMLCU/40464 | J3: 24-Oct-2025 | K3: 46043 | L3: 31-Dec-2025 | M3: Deferred | N3: USD | O3: 93458.11 | P3: 91187251 | Q3: 93458.11 | S3: Accepted | U3: 30-Jul-2026 | CW3: =Table1[[#This Row],[LC Value (USD)]]-Table1[[#This Row],[Value]]-Table1[[#This Row],[Value3]]-Table1[[#This Row],[Value10]]-Table1[[#This Row],[Value17]]-Table1[[#This Row],[Value24]]-Table1[[#This Row],[Value31]]-Table1[[#This Row],[Value38]]-Table1[[#This Row],[Value45]]-Table1[[#This Row],[Value52]]-Table1[[#This Row],[Value59]]-Table1[[#This Row],[Value66]]-Table1[[#This Row],[Value73]] -> 0
A4: 2 | B4: Al Hashar Pharmacy Llc | C4: =_xlfn.XLOOKUP(Table1[[#This Row],[Customer]], 'Cust Data'!D:D, 'Cust Data'!E:E, "N/A") -> Oman | D4: =_xlfn.XLOOKUP(Table1[[#This Row],[Customer]], 'Cust Data'!D:D, 'Cust Data'!C:C, "N/A") -> 2000006 | E4: BANK MUSCAT SA | F4: 2026/ILC/3381 | G4: 180 Days From TCN | H4: BANK MUSCAT OMAN | I4: 26/BMLCU/40579 | J4: 28-Jan-2026 | K4: 46089 | L4: 15-Feb-2026 | M4: Deferred | N4: USD | O4: 237831.61 | P4: 91189924 | Q4: 57415.67 | S4: Accepted | U4: 04-Aug-2026 | W4: 91186097 | X4: 155195.44 | Z4: Accepted | AB4: 04-Aug-2026 | AD4: 91189919 | AE4: 1993.6 | AG4: Accepted | AI4: 04-Aug-2026 | AK4: 91189901 | AL4: 18008.96 | CW4: =Table1[[#This Row],[LC Value (USD)]]-Table1[[#This Row],[Value]]-Table1[[#This Row],[Value3]]-Table1[[#This Row],[Value10]]-Table1[[#This Row],[Value17]]-Table1[[#This Row],[Value24]]-Table1[[#This Row],[Value31]]-Table1[[#This Row],[Value38]]-Table1[[#This Row],[Value45]]-Table1[[#This Row],[Value52]]-Table1[[#This Row],[Value59]]-Table1[[#This Row],[Value66]]-Table1[[#This Row],[Value73]] -> 5217.94
A5: 3 | B5: Al Hashar Pharmacy Llc | C5: =_xlfn.XLOOKUP(Table1[[#This Row],[Customer]], 'Cust Data'!D:D, 'Cust Data'!E:E, "N/A") -> Oman | D5: =_xlfn.XLOOKUP(Table1[[#This Row],[Customer]], 'Cust Data'!D:D, 'Cust Data'!C:C, "N/A") -> 2000006 | E5: BANK MUSCAT SA | F5: 2026/ILC/3388 | G5: 180 Days From TCN | H5: BANK MUSCAT OMAN | I5: 26/BMLCU/40801 | J5: 17-Feb-2026 | K5: 46117 | L5: 15-Mar-2026 | M5: Deferred | N5: USD | O5: 414745.85 | P5: 91195705 | Q5: 355645.85 | S5: Accepted | U5: 25-Aug-2026 | W5: 91196156 | X5: 59100 | Z5: Accepted | AA5: 25-Aug-2026 | CW5: =Table1[[#This Row],[LC Value (USD)]]-Table1[[#This Row],[Value]]-Table1[[#This Row],[Value3]]-Table1[[#This Row],[Value10]]-Table1[[#This Row],[Value17]]-Table1[[#This Row],[Value24]]-Table1[[#This Row],[Value31]]-Table1[[#This Row],[Value38]]-Table1[[#This Row],[Value45]]-Table1[[#This Row],[Value52]]-Table1[[#This Row],[Value59]]-Table1[[#This Row],[Value66]]-Table1[[#This Row],[Value73]] -> 0
A6: 4 | B6: Al Hashar Pharmacy Llc | C6: =_xlfn.XLOOKUP(Table1[[#This Row],[Customer]], 'Cust Data'!D:D, 'Cust Data'!E:E, "N/A") -> Oman | D6: =_xlfn.XLOOKUP(Table1[[#This Row],[Customer]], 'Cust Data'!D:D, 'Cust Data'!C:C, "N/A") -> 2000006 | E6: BANK MUSCAT SA | F6: 2026/ILC/3393 | G6: 180 Days From TCN | H6: BANK MUSCAT OMAN | I6: 26/BMLCU/40829 | J6: 22-Feb-2026 | K6: 46117 | L6: 15-Mar-2026 | M6: Deferred | N6: USD | O6: 172096.92 | P6: 91197426 | Q6: 172096.92 | CW6: =Table1[[#This Row],[LC Value (USD)]]-Table1[[#This Row],[Value]]-Table1[[#This Row],[Value3]]-Table1[[#This Row],[Value10]]-Table1[[#This Row],[Value17]]-Table1[[#This Row],[Value24]]-Table1[[#This Row],[Value31]]-Table1[[#This Row],[Value38]]-Table1[[#This Row],[Value45]]-Table1[[#This Row],[Value52]]-Table1[[#This Row],[Value59]]-Table1[[#This Row],[Value66]]-Table1[[#This Row],[Value73]] -> 0
A7: 5 | B7: Al Hikma Fzco Iraq | C7: =_xlfn.XLOOKUP(Table1[[#This Row],[Customer]], 'Cust Data'!D:D, 'Cust Data'!E:E, "N/A") -> Iraq | D7: =_xlfn.XLOOKUP(Table1[[#This Row],[Customer]], 'Cust Data'!D:D, 'Cust Data'!C:C, "N/A") -> 2000018 | E7: INMA | F7: TF2605000007JEDX | G7: 180 Days From Shipment | H7: INT. DEV. BANK | I7: OLCD001260139 | J7: 18-Feb-2026 | K7: 46154 | L7: 28-Apr-2026 | M7: Deferred | N7: USD | O7: 750804.98 | P7: 91200826 | Q7: 650451 | W7: 91206415 | X7: 100351.3 | CW7: =Table1[[#This Row],[LC Value (USD)]]-Table1[[#This Row],[Value]]-Table1[[#This Row],[Value3]]-Table1[[#This Row],[Value10]]-Table1[[#This Row],[Value17]]-Table1[[#This Row],[Value24]]-Table1[[#This Row],[Value31]]-Table1[[#This Row],[Value38]]-Table1[[#This Row],[Value45]]-Table1[[#This Row],[Value52]]-Table1[[#This Row],[Value59]]-Table1[[#This Row],[Value66]]-Table1[[#This Row],[Value73]] -> 2.68
A8: 6 | B8: Samt For Medical Supplies | C8: =_xlfn.XLOOKUP(Table1[[#This Row],[Customer]], 'Cust Data'!D:D, 'Cust Data'!E:E, "N/A") -> Libya | D8: =_xlfn.XLOOKUP(Table1[[#This Row],[Customer]], 'Cust Data'!D:D, 'Cust Data'!C:C, "N/A") -> 2000012 | E8: ABC | F8: ELC26BH00427 | G8: 60 Calendar Days After Presentation of Complied Documents | H8: JUMHOURIA BANK | I8: 777LC09260770017 | J8: 18-Mar-2026 | K8: 46189 | L8: 06-May-2026 | M8: Deferred | N8: USD | O8: 200806.15 | P8: 91199933 | Q8: 200806.15 | CW8: =Table1[[#This Row],[LC Value (USD)]]-Table1[[#This Row],[Value]]-Table1[[#This Row],[Value3]]-Table1[[#This Row],[Value10]]-Table1[[#This Row],[Value17]]-Table1[[#This Row],[Value24]]-Table1[[#This Row],[Value31]]-Table1[[#This Row],[Value38]]-Table1[[#This Row],[Value45]]-Table1[[#This Row],[Value52]]-Table1[[#This Row],[Value59]]-Table1[[#This Row],[Value66]]-Table1[[#This Row],[Value73]] -> 0
A9: 7 | B9: Al Hikma Fzco Iraq | C9: =_xlfn.XLOOKUP(Table1[[#This Row],[Customer]], 'Cust Data'!D:D, 'Cust Data'!E:E, "N/A") -> Iraq | D9: =_xlfn.XLOOKUP(Table1[[#This Row],[Customer]], 'Cust Data'!D:D, 'Cust Data'!C:C, "N/A") -> 2000018 | E9: INMA | F9: TF2608300001JEDX | G9: 180 Days From Shipment | H9: INT. DEV. BANK | I9: OLCD001260145 | J9: 18-Mar-2026 | K9: 46154 | L9: 27-Apr-2026 | M9: Deferred | N9: USD | O9: 747352.2 | P9: 91206417 | Q9: 374620.58 | W9: 91213842 | X9: 286840.8 | AD9: 91213847 | AE9: 39033.9 | CW9: =Table1[[#This Row],[LC Value (USD)]]-Table1[[#This Row],[Value]]-Table1[[#This Row],[Value3]]-Table1[[#This Row],[Value10]]-Table1[[#This Row],[Value17]]-Table1[[#This Row],[Value24]]-Table1[[#This Row],[Value31]]-Table1[[#This Row],[Value38]]-Table1[[#This Row],[Value45]]-Table1[[#This Row],[Value52]]-Table1[[#This Row],[Value59]]-Table1[[#This Row],[Value66]]-Table1[[#This Row],[Value73]] -> 46856.92
A10: 8 | B10: Zenith Pharma | C10: =_xlfn.XLOOKUP(Table1[[#This Row],[Customer]], 'Cust Data'!D:D, 'Cust Data'!E:E, "N/A") -> Morocco | D10: =_xlfn.XLOOKUP(Table1[[#This Row],[Customer]], 'Cust Data'!D:D, 'Cust Data'!C:C, "N/A") -> 2000022 | E10: ANB | F10: EXWC020935 | G10: 180 Days From Shipment Beneficiary Draft | H10: BANQUE POPULAIRE DE | I10: TF2606933771 | J10: 10-Mar-2026 | K10: 46345 | L10: 30-Oct-2026 | M10: Deferred | N10: USD | O10: 2881945.4 | P10: 91206606 | Q10: 438144 | S10: Accepted | U10: 09-Oct-2026 | W10: 91206608 | X10: 310587.01 | Z10: Accepted | AB10: 09-Oct-2026 | AD10: 91206609 | AE10: 37391.84 | AG10: Accepted | AI10: 09-Oct-2026 | AK10: 91213275 | AL10: 84657.9 | AR10: 91213277 | AS10: 592683.1 | CW10: =Table1[[#This Row],[LC Value (USD)]]-Table1[[#This Row],[Value]]-Table1[[#This Row],[Value3]]-Table1[[#This Row],[Value10]]-Table1[[#This Row],[Value17]]-Table1[[#This Row],[Value24]]-Table1[[#This Row],[Value31]]-Table1[[#This Row],[Value38]]-Table1[[#This Row],[Value45]]-Table1[[#This Row],[Value52]]-Table1[[#This Row],[Value59]]-Table1[[#This Row],[Value66]]-Table1[[#This Row],[Value73]] -> 1418481.5
A11: 9 | B11: Lanamed Pharmaceuticals Import | C11: =_xlfn.XLOOKUP(Table1[[#This Row],[Customer]], 'Cust Data'!D:D, 'Cust Data'!E:E, "N/A") -> Ethiopia | D11: =_xlfn.XLOOKUP(Table1[[#This Row],[Customer]], 'Cust Data'!D:D, 'Cust Data'!C:C, "N/A") -> 2001209 | E11: QNB | F11: ELC/2026/00441QA | G11: At Sight | H11: AWASH BANK | I11: AB1000ILC0074126 | J11: 24-Mar-2026 | K11: 46194 | L11: 01-Jun-2026 | M11: Deferred | N11: USD | O11: 52678.12 | P11: 91206748 | Q11: 46729 | CW11: =Table1[[#This Row],[LC Value (USD)]]-Table1[[#This Row],[Value]]-Table1[[#This Row],[Value3]]-Table1[[#This Row],[Value10]]-Table1[[#This Row],[Value17]]-Table1[[#This Row],[Value24]]-Table1[[#This Row],[Value31]]-Table1[[#This Row],[Value38]]-Table1[[#This Row],[Value45]]-Table1[[#This Row],[Value52]]-Table1[[#This Row],[Value59]]-Table1[[#This Row],[Value66]]-Table1[[#This Row],[Value73]] -> 5949.12
A12: 10 | B12: Kare Pharmaceutical Plc | C12: =_xlfn.XLOOKUP(Table1[[#This Row],[Customer]], 'Cust Data'!D:D, 'Cust Data'!E:E, "N/A") -> Ethiopia | D12: =_xlfn.XLOOKUP(Table1[[#This Row],[Customer]], 'Cust Data'!D:D, 'Cust Data'!C:C, "N/A") -> 2001332 | E12: QNB | F12: ELC/2026/00478QA | G12: At Sight | H12: GADAABANK | I12: GDAIBDIMP0083/26 | J12: 25-Mar-2026 | K12: 46195 | L12: 01-Jun-2026 | M12: Deferred | N12: USD | O12: 475381.73 | P12: 91205843 | Q12: 389958.34 | W12: 91214870 | X12: 85423.4 | CW12: =Table1[[#This Row],[LC Value (USD)]]-Table1[[#This Row],[Value]]-Table1[[#This Row],[Value3]]-Table1[[#This Row],[Value10]]-Table1[[#This Row],[Value17]]-Table1[[#This Row],[Value24]]-Table1[[#This Row],[Value31]]-Table1[[#This Row],[Value38]]-Table1[[#This Row],[Value45]]-Table1[[#This Row],[Value52]]-Table1[[#This Row],[Value59]]-Table1[[#This Row],[Value66]]-Table1[[#This Row],[Value73]] -> -0.01
A13: 11 | B13: Al Hashar Pharmacy Llc | C13: =_xlfn.XLOOKUP(Table1[[#This Row],[Customer]], 'Cust Data'!D:D, 'Cust Data'!E:E, "N/A") -> Oman | D13: =_xlfn.XLOOKUP(Table1[[#This Row],[Customer]], 'Cust Data'!D:D, 'Cust Data'!C:C, "N/A") -> 2000006 | E13: BANK MUSCAT SA | F13: 2026/ILC/3407 | G13: 180 Days From TCN | H13: BANK MUSCAT OMAN | I13: 26/BMLCU/41157 | J13: 46112 | K13: 46148 | L13: 46127 | M13: Deferred | N13: USD | O13: 335479.61 | P13: 91205473 | CW13: =Table1[[#This Row],[LC Value (USD)]]-Table1[[#This Row],[Value]]-Table1[[#This Row],[Value3]]-Table1[[#This Row],[Value10]]-Table1[[#This Row],[Value17]]-Table1[[#This Row],[Value24]]-Table1[[#This Row],[Value31]]-Table1[[#This Row],[Value38]]-Table1[[#This Row],[Value45]]-Table1[[#This Row],[Value52]]-Table1[[#This Row],[Value59]]-Table1[[#This Row],[Value66]]-Table1[[#This Row],[Value73]] -> 335479.61
A14: 12 | B14: Al Hashar Pharmacy Llc | C14: =_xlfn.XLOOKUP(Table1[[#This Row],[Customer]], 'Cust Data'!D:D, 'Cust Data'!E:E, "N/A") -> Oman | D14: =_xlfn.XLOOKUP(Table1[[#This Row],[Customer]], 'Cust Data'!D:D, 'Cust Data'!C:C, "N/A") -> 2000006 | E14: BANK MUSCAT SA | F14: 2026/ILC/3417 | G14: 180 Days From TCN | H14: BANK MUSCAT OMAN | I14: 26/BMLCU/41321 | J14: 46134 | K14: 46178 | L14: 46157 | M14: Deferred | N14: USD | O14: 341988.22 | P14: 91213468 | CW14: =Table1[[#This Row],[LC Value (USD)]]-Table1[[#This Row],[Value]]-Table1[[#This Row],[Value3]]-Table1[[#This Row],[Value10]]-Table1[[#This Row],[Value17]]-Table1[[#This Row],[Value24]]-Table1[[#This Row],[Value31]]-Table1[[#This Row],[Value38]]-Table1[[#This Row],[Value45]]-Table1[[#This Row],[Value52]]-Table1[[#This Row],[Value59]]-Table1[[#This Row],[Value66]]-Table1[[#This Row],[Value73]] -> 341988.22
A15: 13 | B15: Al Hashar Pharmacy Llc | C15: =_xlfn.XLOOKUP(Table1[[#This Row],[Customer]], 'Cust Data'!D:D, 'Cust Data'!E:E, "N/A") -> Oman | D15: =_xlfn.XLOOKUP(Table1[[#This Row],[Customer]], 'Cust Data'!D:D, 'Cust Data'!C:C, "N/A") -> 2000006 | E15: BANK MUSCAT SA | F15: 2026/ILC/3405 | G15: 180 Days From TCN | H15: BANK MUSCAT OMAN | I15: 26/BMLCU/41031 | J15: 46107 | K15: 46148 | L15: 46127 | M15: Deferred | N15: USD | O15: 775682.65 | P15: 91202373 | W15: 91202528 | CW15: =Table1[[#This Row],[LC Value (USD)]]-Table1[[#This Row],[Value]]-Table1[[#This Row],[Value3]]-Table1[[#This Row],[Value10]]-Table1[[#This Row],[Value17]]-Table1[[#This Row],[Value24]]-Table1[[#This Row],[Value31]]-Table1[[#This Row],[Value38]]-Table1[[#This Row],[Value45]]-Table1[[#This Row],[Value52]]-Table1[[#This Row],[Value59]]-Table1[[#This Row],[Value66]]-Table1[[#This Row],[Value73]] -> 775682.65
A16: 14 | B16: Al Hikma Fzco Iraq | C16: =_xlfn.XLOOKUP(Table1[[#This Row],[Customer]], 'Cust Data'!D:D, 'Cust Data'!E:E, "N/A") -> Iraq | D16: =_xlfn.XLOOKUP(Table1[[#This Row],[Customer]], 'Cust Data'!D:D, 'Cust Data'!C:C, "N/A") -> 2000018 | E16: INMA | F16: TF2612500004JEDX | G16: 180 Days From TCN | H16: INT. DEV. BANK | I16: OLCD001260151 | J16: 46146 | K16: 46229 | L16: 46214 | M16: Deferred | N16: USD | O16: 770487.61 | P16: 91219417 | Q16: 128390 | W16: 91219491 | X16: 47539.5 | AD16: 91219571 | AE16: 37818.2 | AK16: 91226392 | AL16: 341377.25 | AR16: 91226395 | AS16: 215275.4 | CW16: =Table1[[#This Row],[LC Value (USD)]]-Table1[[#This Row],[Value]]-Table1[[#This Row],[Value3]]-Table1[[#This Row],[Value10]]-Table1[[#This Row],[Value17]]-Table1[[#This Row],[Value24]]-Table1[[#This Row],[Value31]]-Table1[[#This Row],[Value38]]-Table1[[#This Row],[Value45]]-Table1[[#This Row],[Value52]]-Table1[[#This Row],[Value59]]-Table1[[#This Row],[Value66]]-Table1[[#This Row],[Value73]] -> 87.26
A17: 15 | B17: Al Hashar Pharmacy Llc | C17: =_xlfn.XLOOKUP(Table1[[#This Row],[Customer]], 'Cust Data'!D:D, 'Cust Data'!E:E, "N/A") -> Oman | D17: =_xlfn.XLOOKUP(Table1[[#This Row],[Customer]], 'Cust Data'!D:D, 'Cust Data'!C:C, "N/A") -> 2000006 | E17: BANK MUSCAT SA | F17: 2026/ILC/3432 | G17: 180 Days From TCN | H17: BANK DHOFAR | I17: OLCT260054 | J17: 46162 | K17: 46209 | L17: 46188 | M17: Deferred | N17: USD | O17: 475824.47 | P17: 91219680 | Q17: 105721 | W17: 91219652 | X17: 657.72 | AD17: 91219676 | AE17: 33645.72 | AK17: 91219677 | AL17: 11803.26 | AR17: 91219678 | AS17: 29952.18 | AY17: 91219681 | AZ17: 24066.72 | BF17: 91219690 | BG17: 11078.72 | BM17: 91219898 | BN17: 218152.89 | CW17: =Table1[[#This Row],[LC Value (USD)]]-Table1[[#This Row],[Value]]-Table1[[#This Row],[Value3]]-Table1[[#This Row],[Value10]]-Table1[[#This Row],[Value17]]-Table1[[#This Row],[Value24]]-Table1[[#This Row],[Value31]]-Table1[[#This Row],[Value38]]-Table1[[#This Row],[Value45]]-Table1[[#This Row],[Value52]]-Table1[[#This Row],[Value59]]-Table1[[#This Row],[Value66]]-Table1[[#This Row],[Value73]] -> 40746.26
A18: 16 | B18: Unicare Medical | C18: =_xlfn.XLOOKUP(Table1[[#This Row],[Customer]], 'Cust Data'!D:D, 'Cust Data'!E:E, "N/A") -> UAE | D18: =_xlfn.XLOOKUP(Table1[[#This Row],[Customer]], 'Cust Data'!D:D, 'Cust Data'!C:C, "N/A") -> 2002279 | E18: ENBD | F18: ENSALA26000150 | G18: 90 Days From Dn | I18: AWAELCU260068 | J18: 46162 | K18: 46223 | L18: 46202 | M18: Deferred | N18: USD | O18: 90596 | CW18: =Table1[[#This Row],[LC Value (USD)]]-Table1[[#This Row],[Value]]-Table1[[#This Row],[Value3]]-Table1[[#This Row],[Value10]]-Table1[[#This Row],[Value17]]-Table1[[#This Row],[Value24]]-Table1[[#This Row],[Value31]]-Table1[[#This Row],[Value38]]-Table1[[#This Row],[Value45]]-Table1[[#This Row],[Value52]]-Table1[[#This Row],[Value59]]-Table1[[#This Row],[Value66]]-Table1[[#This Row],[Value73]] -> 90596
A19: 17 | B19: Tracon Trading Plc | C19: =_xlfn.XLOOKUP(Table1[[#This Row],[Customer]], 'Cust Data'!D:D, 'Cust Data'!E:E, "N/A") -> Ethiopia | D19: =_xlfn.XLOOKUP(Table1[[#This Row],[Customer]], 'Cust Data'!D:D, 'Cust Data'!C:C, "N/A") -> 2001210 | E19: BSF | F19: ELCCB26001530DPR001 | G19: At Sight | H19: AWASH BANK | I19: AB1000ILC0132126 | J19: 46162 | K19: 46251 | L19: 46223 | M19: Sight | N19: USD | O19: 563636.54 | P19: 91220291 | Q19: 45607.32 | W19: 91220476 | X19: 394993.25 | CW19: =Table1[[#This Row],[LC Value (USD)]]-Table1[[#This Row],[Value]]-Table1[[#This Row],[Value3]]-Table1[[#This Row],[Value10]]-Table1[[#This Row],[Value17]]-Table1[[#This Row],[Value24]]-Table1[[#This Row],[Value31]]-Table1[[#This Row],[Value38]]-Table1[[#This Row],[Value45]]-Table1[[#This Row],[Value52]]-Table1[[#This Row],[Value59]]-Table1[[#This Row],[Value66]]-Table1[[#This Row],[Value73]] -> 123035.97
A20: 18 | B20: El Hakeem For Importing Pharmaceutical | C20: =_xlfn.XLOOKUP(Table1[[#This Row],[Customer]], 'Cust Data'!D:D, 'Cust Data'!E:E, "N/A") -> Libya | D20: =_xlfn.XLOOKUP(Table1[[#This Row],[Customer]], 'Cust Data'!D:D, 'Cust Data'!C:C, "N/A") -> 2001514 | E20: ABC | F20: ELC26BH00858 | G20: 60 Calendar Days After Presentation Of Complied Documents | H20: ALWAHA BANK | I20: ILC310/159/26 | J20: 46166 | K20: 46257 | L20: 46257 | M20: Deferred | N20: USD | O20: 148875.1 | CW20: =Table1[[#This Row],[LC Value (USD)]]-Table1[[#This Row],[Value]]-Table1[[#This Row],[Value3]]-Table1[[#This Row],[Value10]]-Table1[[#This Row],[Value17]]-Table1[[#This Row],[Value24]]-Table1[[#This Row],[Value31]]-Table1[[#This Row],[Value38]]-Table1[[#This Row],[Value45]]-Table1[[#This Row],[Value52]]-Table1[[#This Row],[Value59]]-Table1[[#This Row],[Value66]]-Table1[[#This Row],[Value73]] -> 148875.1
A21: 19 | B21: Samt For Medical Supplies | C21: =_xlfn.XLOOKUP(Table1[[#This Row],[Customer]], 'Cust Data'!D:D, 'Cust Data'!E:E, "N/A") -> Libya | D21: =_xlfn.XLOOKUP(Table1[[#This Row],[Customer]], 'Cust Data'!D:D, 'Cust Data'!C:C, "N/A") -> 2000012 | E21: ABC | F21: ELC26BH00911 | G21: 60 Calendar Days After Presentation Of Complied Documents | H21: JUMHOURIA BANK | I21: 777LC09261550003 | J21: 46177 | K21: 46267 | L21: 46247 | M21: Deferred | N21: USD | O21: 753141 | CW21: =Table1[[#This Row],[LC Value (USD)]]-Table1[[#This Row],[Value]]-Table1[[#This Row],[Value3]]-Table1[[#This Row],[Value10]]-Table1[[#This Row],[Value17]]-Table1[[#This Row],[Value24]]-Table1[[#This Row],[Value31]]-Table1[[#This Row],[Value38]]-Table1[[#This Row],[Value45]]-Table1[[#This Row],[Value52]]-Table1[[#This Row],[Value59]]-Table1[[#This Row],[Value66]]-Table1[[#This Row],[Value73]] -> 753141
A22: 20 | B22: Al Hashar Pharmacy Llc | C22: =_xlfn.XLOOKUP(Table1[[#This Row],[Customer]], 'Cust Data'!D:D, 'Cust Data'!E:E, "N/A") -> Oman | D22: =_xlfn.XLOOKUP(Table1[[#This Row],[Customer]], 'Cust Data'!D:D, 'Cust Data'!C:C, "N/A") -> 2000006 | E22: RIYAD BANK | F22: JXP7000344 | G22: 180 Days From TCN | H22: BANK DHOFAR | I22: OLCT260073 | J22: 46195 | K22: 46239 | L22: 46218 | M22: Deferred | N22: USD | O22: 648430.58
N23: GRAND TOTAL | O23: =SUM(INDIRECT("o3:o" &ROW()-1)) -> 10931243 | CW23: =SUBTOTAL(109,CW3:CW16) -> 2929745.9

Sheet Certificate of Analysis
B4: Certificate of Analysis
B8: ='cover Letter print'!B2 -> Date: | G8: 46167
B9: Customer Name: | G9: ='cover Letter print'!H12 -> Al Hashar Pharmacy Llc
B10: LC No: | G10: ='cover Letter print'!Q2 -> OLCT260054
B11: Invoice No: | G11: ='LC Tracker'!P19 -> 91220291
B12: HS Code: | G12: 30049090
B13: TIN Number: | G13: 0000009646
B16: Sincerely,
B18: Tabuk Pharmaceuticals Manufacturing Company

Sheet Summary
A1: LC PORTFOLIO SUMMARY
A3: LC BREAKDOWN | H3: Total LC Value | I3: Total Invoiced | J3: Total Remaining | K3: # of LCs
A4: LC # | B4: Customer | C4: Country | D4: LC Value (USD) | E4: Remaining (USD) | F4: Status | H4: =SUM('LC Tracker'!O3:O16) -> 8250739.1 | I4: =SUM('Invoice Detail'!D3:D24) -> 4550592.9 | J4: =SUM('LC Tracker'!CW3:CW12) -> 1476508.2 | K4: =COUNT('LC Tracker'!A3:A16) -> 14
A5: 1 | B5: ='LC Tracker'!B3 -> Al Hashar Pharmacy Llc | C5: ='LC Tracker'!C3 -> Oman | D5: ='LC Tracker'!O3 -> 93458.11 | E5: ='LC Tracker'!O3+-'LC Tracker'!Q3-'LC Tracker'!X3-'LC Tracker'!AE3-'LC Tracker'!AL3-'LC Tracker'!AS3-'LC Tracker'!AZ3-'LC Tracker'!BG3-'LC Tracker'!BN3-'LC Tracker'!BU3-'LC Tracker'!CB3-'LC Tracker'!CI3-'LC Tracker'!CP3 -> 0 | F5: =IF(E5<=0,"Fully Drawn","Open") -> Fully Drawn
A6: 2 | B6: ='LC Tracker'!B4 -> Al Hashar Pharmacy Llc | C6: ='LC Tracker'!C4 -> Oman | D6: ='LC Tracker'!O4 -> 237831.61 | E6: ='LC Tracker'!O4+-'LC Tracker'!Q4-'LC Tracker'!X4-'LC Tracker'!AE4-'LC Tracker'!AL4-'LC Tracker'!AS4-'LC Tracker'!AZ4-'LC Tracker'!BG4-'LC Tracker'!BN4-'LC Tracker'!BU4-'LC Tracker'!CB4-'LC Tracker'!CI4-'LC Tracker'!CP4 -> 5217.94 | F6: =IF(E6<=0,"Fully Drawn","Open") -> Open
A7: 3 | B7: ='LC Tracker'!B5 -> Al Hashar Pharmacy Llc | C7: ='LC Tracker'!C5 -> Oman | D7: ='LC Tracker'!O5 -> 414745.85 | E7: ='LC Tracker'!O5+-'LC Tracker'!Q5-'LC Tracker'!X5-'LC Tracker'!AE5-'LC Tracker'!AL5-'LC Tracker'!AS5-'LC Tracker'!AZ5-'LC Tracker'!BG5-'LC Tracker'!BN5-'LC Tracker'!BU5-'LC Tracker'!CB5-'LC Tracker'!CI5-'LC Tracker'!CP5 -> 0 | F7: =IF(E7<=0,"Fully Drawn","Open") -> Fully Drawn
A8: 4 | B8: ='LC Tracker'!B6 -> Al Hashar Pharmacy Llc | C8: ='LC Tracker'!C6 -> Oman | D8: ='LC Tracker'!O6 -> 172096.92 | E8: ='LC Tracker'!O6+-'LC Tracker'!Q6-'LC Tracker'!X6-'LC Tracker'!AE6-'LC Tracker'!AL6-'LC Tracker'!AS6-'LC Tracker'!AZ6-'LC Tracker'!BG6-'LC Tracker'!BN6-'LC Tracker'!BU6-'LC Tracker'!CB6-'LC Tracker'!CI6-'LC Tracker'!CP6 -> 0 | F8: =IF(E8<=0,"Fully Drawn","Open") -> Fully Drawn
A9: 5 | B9: ='LC Tracker'!B7 -> Al Hikma Fzco Iraq | C9: ='LC Tracker'!C7 -> Iraq | D9: ='LC Tracker'!O7 -> 750804.98 | E9: ='LC Tracker'!O7+-'LC Tracker'!Q7-'LC Tracker'!X7-'LC Tracker'!AE7-'LC Tracker'!AL7-'LC Tracker'!AS7-'LC Tracker'!AZ7-'LC Tracker'!BG7-'LC Tracker'!BN7-'LC Tracker'!BU7-'LC Tracker'!CB7-'LC Tracker'!CI7-'LC Tracker'!CP7 -> 2.68 | F9: =IF(E9<=0,"Fully Drawn","Open") -> Open
A10: 6 | B10: ='LC Tracker'!B8 -> Samt For Medical Supplies | C10: ='LC Tracker'!C8 -> Libya | D10: ='LC Tracker'!O8 -> 200806.15 | E10: ='LC Tracker'!O8+-'LC Tracker'!Q8-'LC Tracker'!X8-'LC Tracker'!AE8-'LC Tracker'!AL8-'LC Tracker'!AS8-'LC Tracker'!AZ8-'LC Tracker'!BG8-'LC Tracker'!BN8-'LC Tracker'!BU8-'LC Tracker'!CB8-'LC Tracker'!CI8-'LC Tracker'!CP8 -> 0 | F10: =IF(E10<=0,"Fully Drawn","Open") -> Fully Drawn
A11: 7 | B11: ='LC Tracker'!B9 -> Al Hikma Fzco Iraq | C11: ='LC Tracker'!C9 -> Iraq | D11: ='LC Tracker'!O9 -> 747352.2 | E11: ='LC Tracker'!O9+-'LC Tracker'!Q9-'LC Tracker'!X9-'LC Tracker'!AE9-'LC Tracker'!AL9-'LC Tracker'!AS9-'LC Tracker'!AZ9-'LC Tracker'!BG9-'LC Tracker'!BN9-'LC Tracker'!BU9-'LC Tracker'!CB9-'LC Tracker'!CI9-'LC Tracker'!CP9 -> 46856.92 | F11: =IF(E11<=0,"Fully Drawn","Open") -> Open
A12: 8 | B12: ='LC Tracker'!#REF! -> #REF! | C12: ='LC Tracker'!#REF! -> #REF! | D12: ='LC Tracker'!#REF! -> #REF! | E12: ='LC Tracker'!#REF!+-'LC Tracker'!#REF!-'LC Tracker'!#REF!-'LC Tracker'!#REF!-'LC Tracker'!#REF!-'LC Tracker'!#REF!-'LC Tracker'!#REF!-'LC Tracker'!#REF!-'LC Tracker'!#REF!-'LC Tracker'!#REF!-'LC Tracker'!#REF!-'LC Tracker'!#REF!-'LC Tracker'!#REF! -> #REF! | F12: =IF(E12<=0,"Fully Drawn","Open") -> #REF!
A13: 9 | B13: ='LC Tracker'!B10 -> Zenith Pharma | C13: ='LC Tracker'!C10 -> Morocco | D13: ='LC Tracker'!O10 -> 2881945.4 | E13: ='LC Tracker'!O10+-'LC Tracker'!Q10-'LC Tracker'!X10-'LC Tracker'!AE10-'LC Tracker'!AL10-'LC Tracker'!AS10-'LC Tracker'!AZ10-'LC Tracker'!BG10-'LC Tracker'!BN10-'LC Tracker'!BU10-'LC Tracker'!CB10-'LC Tracker'!CI10-'LC Tracker'!CP10 -> 1418481.5 | F13: =IF(E13<=0,"Fully Drawn","Open") -> Open
A14: 10 | B14: ='LC Tracker'!B11 -> Lanamed Pharmaceuticals Import | C14: ='LC Tracker'!C11 -> Ethiopia | D14: ='LC Tracker'!O11 -> 52678.12 | E14: ='LC Tracker'!O11+-'LC Tracker'!Q11-'LC Tracker'!X11-'LC Tracker'!AE11-'LC Tracker'!AL11-'LC Tracker'!AS11-'LC Tracker'!AZ11-'LC Tracker'!BG11-'LC Tracker'!BN11-'LC Tracker'!BU11-'LC Tracker'!CB11-'LC Tracker'!CI11-'LC Tracker'!CP11 -> 5949.12 | F14: =IF(E14<=0,"Fully Drawn","Open") -> Open
A15: 11 | B15: Kare | C15: Ethiopia | D15: ='LC Tracker'!O12 -> 475381.73 | E15: ='LC Tracker'!O12+-'LC Tracker'!Q12-'LC Tracker'!X12-'LC Tracker'!AE12-'LC Tracker'!AL12-'LC Tracker'!AS12-'LC Tracker'!AZ12-'LC Tracker'!BG12-'LC Tracker'!BN12-'LC Tracker'!BU12-'LC Tracker'!CB12-'LC Tracker'!CI12-'LC Tracker'!CP12 -> -0.01 | F15: =IF(E15<=0,"Fully Drawn","Open") -> Fully Drawn
A16: 12 | B16: ='LC Tracker'!B13 -> Al Hashar Pharmacy Llc | C16: ='LC Tracker'!C13 -> Oman | D16: ='LC Tracker'!O13 -> 335479.61 | E16: ='LC Tracker'!O13+-'LC Tracker'!Q13-'LC Tracker'!X13-'LC Tracker'!AE13-'LC Tracker'!AL13-'LC Tracker'!AS13-'LC Tracker'!AZ13-'LC Tracker'!BG13-'LC Tracker'!BN13-'LC Tracker'!BU13-'LC Tracker'!CB13-'LC Tracker'!CI13-'LC Tracker'!CP13 -> 335479.61 | F16: =IF(E16<=0,"Fully Drawn","Open") -> Open
A17: 13 | B17: ='LC Tracker'!B14 -> Al Hashar Pharmacy Llc | C17: ='LC Tracker'!C14 -> Oman | D17: ='LC Tracker'!O14 -> 341988.22 | E17: ='LC Tracker'!O14+-'LC Tracker'!Q14-'LC Tracker'!X14-'LC Tracker'!AE14-'LC Tracker'!AL14-'LC Tracker'!AS14-'LC Tracker'!AZ14-'LC Tracker'!BG14-'LC Tracker'!BN14-'LC Tracker'!BU14-'LC Tracker'!CB14-'LC Tracker'!CI14-'LC Tracker'!CP14 -> 341988.22 | F17: =IF(E17<=0,"Fully Drawn","Open") -> Open
A18: 14 | B18: ='LC Tracker'!B15 -> Al Hashar Pharmacy Llc | C18: ='LC Tracker'!C15 -> Oman | D18: ='LC Tracker'!O15 -> 775682.65 | E18: ='LC Tracker'!O15+-'LC Tracker'!Q15-'LC Tracker'!X15-'LC Tracker'!AE15-'LC Tracker'!AL15-'LC Tracker'!AS15-'LC Tracker'!AZ15-'LC Tracker'!BG15-'LC Tracker'!BN15-'LC Tracker'!BU15-'LC Tracker'!CB15-'LC Tracker'!CI15-'LC Tracker'!CP15 -> 775682.65 | F18: =IF(E18<=0,"Fully Drawn","Open") -> Open
A19: 15 | B19: ='LC Tracker'!B16 -> Al Hikma Fzco Iraq | C19: ='LC Tracker'!C16 -> Iraq | D19: ='LC Tracker'!O16 -> 770487.61 | E19: ='LC Tracker'!O16+-'LC Tracker'!Q16-'LC Tracker'!X16-'LC Tracker'!AE16-'LC Tracker'!AL16-'LC Tracker'!AS16-'LC Tracker'!AZ16-'LC Tracker'!BG16-'LC Tracker'!BN16-'LC Tracker'!BU16-'LC Tracker'!CB16-'LC Tracker'!CI16-'LC Tracker'!CP16 -> 87.26 | F19: =IF(E19<=0,"Fully Drawn","Open") -> Open
A20: 16 | B20: ='LC Tracker'!B17 -> Al Hashar Pharmacy Llc | C20: ='LC Tracker'!C17 -> Oman | D20: ='LC Tracker'!O17 -> 475824.47 | E20: ='LC Tracker'!O17+-'LC Tracker'!Q17-'LC Tracker'!X17-'LC Tracker'!AE17-'LC Tracker'!AL17-'LC Tracker'!AS17-'LC Tracker'!AZ17-'LC Tracker'!BG17-'LC Tracker'!BN17-'LC Tracker'!BU17-'LC Tracker'!CB17-'LC Tracker'!CI17-'LC Tracker'!CP17 -> 40746.26 | F20: =IF(E20<=0,"Fully Drawn","Open") -> Open
A21: 17 | B21: ='LC Tracker'!B18 -> Unicare Medical | C21: ='LC Tracker'!C18 -> UAE | D21: ='LC Tracker'!O18 -> 90596 | E21: ='LC Tracker'!O18+-'LC Tracker'!Q18-'LC Tracker'!X18-'LC Tracker'!AE18-'LC Tracker'!AL18-'LC Tracker'!AS18-'LC Tracker'!AZ18-'LC Tracker'!BG18-'LC Tracker'!BN18-'LC Tracker'!BU18-'LC Tracker'!CB18-'LC Tracker'!CI18-'LC Tracker'!CP18 -> 90596 | F21: =IF(E21<=0,"Fully Drawn","Open") -> Open
A22: 18 | B22: ='LC Tracker'!B19 -> Tracon Trading Plc | C22: ='LC Tracker'!C19 -> Ethiopia | D22: ='LC Tracker'!O19 -> 563636.54 | E22: ='LC Tracker'!O19+-'LC Tracker'!Q19-'LC Tracker'!X19-'LC Tracker'!AE19-'LC Tracker'!AL19-'LC Tracker'!AS19-'LC Tracker'!AZ19-'LC Tracker'!BG19-'LC Tracker'!BN19-'LC Tracker'!BU19-'LC Tracker'!CB19-'LC Tracker'!CI19-'LC Tracker'!CP19 -> 123035.97 | F22: =IF(E22<=0,"Fully Drawn","Open") -> Open
A23: 19 | B23: ='LC Tracker'!B20 -> El Hakeem For Importing Pharmaceutical | C23: ='LC Tracker'!C20 -> Libya | D23: ='LC Tracker'!O20 -> 148875.1 | E23: ='LC Tracker'!O20+-'LC Tracker'!Q20-'LC Tracker'!X20-'LC Tracker'!AE20-'LC Tracker'!AL20-'LC Tracker'!AS20-'LC Tracker'!AZ20-'LC Tracker'!BG20-'LC Tracker'!BN20-'LC Tracker'!BU20-'LC Tracker'!CB20-'LC Tracker'!CI20-'LC Tracker'!CP20 -> 148875.1 | F23: =IF(E23<=0,"Fully Drawn","Open") -> Open
A24: 20 | B24: ='LC Tracker'!B21 -> Samt For Medical Supplies | C24: ='LC Tracker'!C21 -> Libya | D24: ='LC Tracker'!O21 -> 753141 | E24: ='LC Tracker'!O21+-'LC Tracker'!Q21-'LC Tracker'!X21-'LC Tracker'!AE21-'LC Tracker'!AL21-'LC Tracker'!AS21-'LC Tracker'!AZ21-'LC Tracker'!BG21-'LC Tracker'!BN21-'LC Tracker'!BU21-'LC Tracker'!CB21-'LC Tracker'!CI21-'LC Tracker'!CP21 -> 753141 | F24: =IF(E24<=0,"Fully Drawn","Open") -> Open
A25: TOTAL | D25: =SUM(D5:D19) -> #REF! | E25: =SUBTOTAL(9,E5:E24) -> #REF!

Sheet lc summary
C4: ='LC Tracker'!B16 -> Al Hikma Fzco Iraq | G4: ='LC Tracker'!F16 -> TF2612500004JEDX
C5: =CONCATENATE("LC Value USD LC #",'LC Tracker'!I16) -> LC Value USD LC #OLCD001260151 | D5: ='LC Tracker'!O16 -> 770487.61 | G5: =CONCATENATE("LC Value USD LC #",'LC Tracker'!M16) -> LC Value USD LC #Deferred | H5: =D5 -> 770487.61
C6: latest Date OS | D6: ='LC Tracker'!L16 -> 46214 | G6: latest Date OS | H6: =D6 -> 46214
C7: Expiry date & place Saudi Arabia | D7: ='LC Tracker'!K16 -> 46229 | G7: Expiry date & place Saudi Arabia | H7: =D7 -> 46229
C8: Remaining Balance | D8: =D5 -> 770487.61 | G8: Remaining Balance | H8: =D8 -> 770487.61
C9: We released# 91219571, 91219491, 91219417 | D9: 213747.7 | G9: We will release | H9: =D9 -> 213747.7
C10: New inoices# 91226395 & 91226392 | D10: 556652.65 | G10: New inoices | H10: =D10 -> 556652.65
C11: Remaining Balance after released New Order | D11: =D5-D9-D10 -> 87.26 | G11: Remaining Balance after released New Order | H11: =D11 -> 87.26

Sheet Cust Data
B2: # | C2: Customer Code | D2: Customer Name | E2: Country
B3: 1 | C3: 2000005 | D3: Alphamed | E3: UAE
B4: 2 | C4: 2000584 | D4: Afaq Int. Marketing & Import Free Zone | E4: Iraq
B5: 3 | C5: 2000028 | D5: Al Hashar Pharmacy (sgh) | E5: Oman
B6: 4 | C6: 2000000 | D6: Al - Mojil Drug Co. | E6: Kuwait
B7: 5 | C7: 2000004 | D7: Ali Abdulwahab Al-mutawa Commercial | E7: Kuwait
B8: 6 | C8: 3555557 | D8: Munir Sukhtian Group Company | E8: Jordan
B9: 7 | C9: 2002042 | D9: Roots Pharmaceutical Company | E9: Kuwait
B10: 8 | C10: 2000009 | D10: Hamad Town Pharmacy | E10: Bahrain
B11: 9 | C11: 2000002 | D11: Behzad Pharmacy | E11: Bahrain
B12: 10 | C12: 2001246 | D12: Ebn Sina Medical | E12: Qatar
B13: 11 | C13: 2001215 | D13: Dawakum Llc | E13: Oman
B14: 12 | C14: 2001307 | D14: Green International Medical Co. Wll | E14: Bahrain
... B133: 131 | C133: 2002279 | D133: Unicare Medical | E133: UAE

Sheet Banks Data
H1: our | J1: there
B2: # | C2: SA Banks | E2: # | F2: Global Banks | H2: ABC | J2: JUMHOURIA BANK
B3: 1 | C3: ABC | E3: 1 | F3: ALWAHA BANK | H3: ADIB | J3: INT. DEV. BANK
B4: 2 | C4: ADIB | E4: 2 | F4: AWASH BANK | H4: ANB | J4: GADAABANK
B5: 3 | C5: ANB | E5: 3 | F5: BANK DHOFAR | H5: ARAB BANK | J5: BANQUE POPULAIRE DE
B6: 4 | C6: ARAB BANK | E6: 4 | F6: BANK MUSCAT OMAN | H6: BANK MUSCAT SA | J6: BANK MUSCAT OMAN
B7: 5 | C7: BANK MUSCAT SA | E7: 5 | F7: BANQUE POPULAIRE DE | H7: BANK OF AFRICA | J7: BANK DHOFAR
B8: 6 | C8: BANK OF AFRICA | E8: 6 | F8: GADAABANK | H8: BILAD | J8: AWASH BANK
B9: 7 | C9: BILAD | E9: 7 | F9: INT. DEV. BANK | H9: BSF | J9: ALWAHA BANK
B10: 8 | C10: BSF | E10: 8 | F10: JUMHOURIA BANK | H10: ENBD
B11: 9 | C11: ENBD | H11: FAB
B12: 10 | C12: FAB | H12: GIB
B13: 11 | C13: GIB | H13: INMA
B14: 12 | C14: INMA | H14: NBI
B15: 13 | C15: NBI | H15: QNB
B16: 14 | C16: QNB | H16: RAJHI BANK
B17: 15 | C17: RAJHI BANK | H17: RIYAD BANK
B18: 16 | C18: RIYAD BANK | H18: SAB
B19: 17 | C19: SAB | H19: SNB
B20: 18 | C20: SNB

Sheet Payment Term
B3: # | C3: Payment Term
B4: 1 | C4: 180 Days From Shipment
B5: 2 | C5: 180 Days From Shipment Beneficiary Draft
B6: 3 | C6: 180 Days From TCN
B7: 4 | C7: 60 Calendar Days After Presentation Of Complied Documents
B8: 5 | C8: 90 Days From Dn
B9: 6 | C9: At Sight

Sheet cover Letter print
B2: Date: | D2: =TODAY() -> 46261 | M2: LC No. | P2: : | Q2: ='LC Tracker'!I17 -> OLCT260054
M3: Our Ref. | P3: : | Q3: ='LC Tracker'!F17 -> 2026/ILC/3432
B4: To: | C4: ='LC Tracker'!E17 -> BANK MUSCAT SA
B5: Trade Operations Centre, Head Office
B8: Subject: Submission of Original Documents
B9: Dears,
B10: =CONCATENATE("Please find enclosed herewith the shipping documents related to LC No.: ",Q2, " as follows:") -> Please find enclosed herewith the shipping documents related to LC No.: OLCT260054 as follows:
B12: Customer Name | G12: : | H12: Al Hashar Pharmacy Llc
B13: Invoice Number(s) | G13: : | H13: =CONCATENATE('LC Tracker'!P17," & ",'LC Tracker'!W17, " & ",'LC Tracker'!AD17, " & ", 'LC Tracker'!AK17, " & ",'LC Tracker'!AR17, " & ",'LC Tracker'!AY17, " & ",'LC Tracker'!BF17, " & ", 'LC Tracker'!BM17, ) -> 91219680 & 91219652 & 91219676 & 91219677 & 91219678 & 91219681 & 91219690 & 91219898
B16: Document Description | G16: Original | O16: Copy
B17: Commercial Invoice | G17: 3 x 2 | O17: -
B18: Certificate of Origin | G18: 1 x 2 | O18: 1 x 2
B19: Certificate of Analysis | G19: 1 x 2 | O19: -
B20: Packing List | G20: 3 x 2 | O20: -
B21: Air Way Bill | G21: 1 x 2 | O21: -
B22: Freight Charges | G22: 1 x 2 | O22: 1 x 2
B23: Copy of L/C | G23: - | O23: 1 x 2
B25: Amount (Figures) | G25: ='LC Tracker'!Q17+'LC Tracker'!X17+'LC Tracker'!AE17+'LC Tracker'!AL17+'LC Tracker'!AS17+'LC Tracker'!AZ17+'LC Tracker'!BG17+'LC Tracker'!BN17 -> 435078.21
B26: Amount (Words) | G26: four hundred thirty-five thousand seventy-eight and 21/100
B27: Currency | G27: USD
B29: Upon receipt of funds from the Issuing Bank, kindly credit the proceeds to our account as follows:
B31: Beneficiary Bank | G31: =CONCATENATE(C4,", Riyadh, Kingdom of Saudi Arabia") -> BANK MUSCAT SA, Riyadh, Kingdom of Saudi Arabia
B32: IBAN/Account No. | G32: SA47 7600 0000 1005 0063 1002
B34: Please ensure the documents are fully compliant; hold the documents and notify us immediately if any discrepancies are identified.
B37: Tabuk Pharmaceuticals Manufacturing Company

Sheet cover Letter print (2)
B2: Date: | D2: =TODAY() -> 46261 | M2: LC No. | P2: : | Q2: ='LC Tracker'!I17 -> OLCT260054
M3: Our Ref. | P3: : | Q3: ='LC Tracker'!F17 -> 2026/ILC/3432
B4: To: | C4: ='LC Tracker'!E17 -> BANK MUSCAT SA
B5: Trade Operations Centre, Head Office
B8: Subject: Submission of Original Documents
B9: Dears,
B10: =CONCATENATE("Please find enclosed herewith the shipping documents related to LC No.: ",Q2, " as follows:") -> Please find enclosed herewith the shipping documents related to LC No.: OLCT260054 as follows:
B12: Customer Name | G12: : | H12: Al Hashar Pharmacy Llc
B13: Invoice Number(s) | G13: : | H13: =CONCATENATE('LC Tracker'!P17," & ",'LC Tracker'!W17, " & ",'LC Tracker'!AD17, " & ", 'LC Tracker'!AK17, " & ",'LC Tracker'!AR17, " & ",'LC Tracker'!AY17, " & ",'LC Tracker'!BF17, " & ", 'LC Tracker'!BM17, ) -> 91219680 & 91219652 & 91219676 & 91219677 & 91219678 & 91219681 & 91219690 & 91219898
B16: Document Description | G16: Original | O16: Copy
B17: Commercial Invoice | G17: 8 | O17: 8
B18: TCN | G18: 3 | O18: -
B19: Copy of L/C | G19: - | O19: 1
B21: Amount (Figures) | G21: 435078/21
B22: Amount (Words) | G22: four hundred thirty-five thousand seventy-eight and 21/100
B23: Currency | G23: USD
B25: Upon receipt of funds from the Issuing Bank, kindly credit the proceeds to our account as follows:
B27: Beneficiary Bank | G27: =CONCATENATE(C4,", Riyadh, Kingdom of Saudi Arabia") -> BANK MUSCAT SA, Riyadh, Kingdom of Saudi Arabia
B28: IBAN/Account No. | G28: SA47 7600 0000 1005 0063 1002
B30: Please ensure the documents are fully compliant; hold the documents and notify us immediately if any discrepancies are identified.
B33: Tabuk Pharmaceuticals Manufacturing Company

Sheet cover Letter print (3)
B2: Date: | D2: =TODAY() -> 46261 | M2: LC No. | P2: : | Q2: ='LC Tracker'!I17 -> OLCT260054
M3: Our Ref. | P3: : | Q3: ='LC Tracker'!F17 -> 2026/ILC/3432
B4: To: | C4: ='LC Tracker'!E17 -> BANK MUSCAT SA
B5: Trade Operations Centre, Head Office
B8: Subject: Submission of Original Documents
B9: Dears,
B10: =CONCATENATE("Please find enclosed herewith the shipping documents related to LC No.: ",Q2, " as follows:") -> Please find enclosed herewith the shipping documents related to LC No.: OLCT260054 as follows:
B12: Customer Name | G12: : | H12: Al Hashar Pharmacy Llc
B13: Invoice Number(s) | G13: : | H13: =CONCATENATE('LC Tracker'!P17," & ",'LC Tracker'!W17, " & ",'LC Tracker'!AD17, " & ", 'LC Tracker'!AK17, " & ",'LC Tracker'!AR17, " & ",'LC Tracker'!AY17, " & ",'LC Tracker'!BF17, " & ", 'LC Tracker'!BM17, ) -> 91219680 & 91219652 & 91219676 & 91219677 & 91219678 & 91219681 & 91219690 & 91219898
B16: Document Description | G16: Original | O16: Copy
B17: Commercial Invoice | G17: 3 x 2 | O17: -
B18: Certificate of Origin | G18: 1 x 2 | O18: 1 x 2
B19: Certificate of Analysis | G19: 1 x 2 | O19: -
B20: Packing List | G20: 3 x 2 | O20: -
B21: Air Way Bill | G21: 1 x 2 | O21: -
B22: Freight Charges | G22: 1 x 2 | O22: 1 x 2
B23: Copy of L/C | G23: - | O23: 1 x 2
B25: Amount (Figures) | G25: ='LC Tracker'!Q17+'LC Tracker'!X17+'LC Tracker'!AE17+'LC Tracker'!AL17+'LC Tracker'!AS17+'LC Tracker'!AZ17+'LC Tracker'!BG17+'LC Tracker'!BN17 -> 435078.21
B26: Amount (Words) | G26: four hundred thirty-five thousand seventy-eight and 21/100
B27: Currency | G27: USD
B29: Upon receipt of funds from the Issuing Bank, kindly credit the proceeds to our account as follows:
B31: Beneficiary Bank | G31: =CONCATENATE(C4,", Riyadh, Kingdom of Saudi Arabia") -> BANK MUSCAT SA, Riyadh, Kingdom of Saudi Arabia
B32: IBAN/Account No. | G32: SA47 7600 0000 1005 0063 1002
B34: Please ensure the documents are fully compliant; hold the documents and notify us immediately if any discrepancies are identified.
B37: Tabuk Pharmaceuticals Manufacturing Company

Sheet Invoice Detail
A1: INVOICE DETAIL — FILL-IN REGISTER
A2: LC # | B2: Customer | C2: Invoice Number | D2: Invoice Value (USD) | E2: Presentation Date | F2: Status | G2: Collection Date | H2: Due Date | I2: Tracking # | J2: Notes
A3: 1/2026 | B3: AL HASHAR PHARMACY LLC | C3: 91187251 | D3: 93458.11 | F3: Accepted | H3: 30-Jul-2026
A4: 2/2026 | B4: AL HASHAR PHARMACY LLC | C4: 91189924 | D4: 57415.67 | F4: Accepted | H4: 04-Aug-2026
A5: 2/2026 | B5: AL HASHAR PHARMACY LLC | C5: 91186097 | D5: 155195.44 | F5: Accepted | H5: 04-Aug-2026
A6: 2/2026 | B6: AL HASHAR PHARMACY LLC | C6: 91189919 | D6: 1993.6 | F6: Accepted | H6: 04-Aug-2026
A7: 2/2026 | B7: AL HASHAR PHARMACY LLC | C7: 91189901 | D7: 18008.96 | F7: Pending | J7: Not yet accepted
A8: 3/2026 | B8: AL HASHAR PHARMACY LLC | C8: 91195705 | D8: 355645.85 | F8: Accepted | H8: 25-Aug-2026
A9: 3/2026 | B9: AL HASHAR PHARMACY LLC | C9: 91196156 | D9: 59100 | F9: Accepted | G9: 25-Aug-2026
A10: 4/2026 | B10: AL HASHAR PHARMACY LLC | C10: 91197426 | D10: 172096.92 | F10: Pending
A11: 5/2026 | B11: Al Hikma FZCO | C11: 91200826 | D11: 650451 | F11: Pending
A12: 5/2026 | B12: Al Hikma FZCO | C12: 91206415 | D12: 100351.3 | F12: Pending
A13: 6/2026 | B13: SMAT FOR MEDICAL SUPPLIES | C13: 91199933 | D13: 200806.15 | F13: Pending
A14: 7/2026 | B14: Al Hikma FZCO | C14: 91206417 | D14: 374620.58 | F14: Pending
A15: 7/2026 | B15: Al Hikma FZCO | C15: 91213842 | D15: 286840.8 | F15: Pending
A16: 7/2026 | B16: Al Hikma FZCO | C16: 91213847 | D16: 39033.9 | F16: Pending
A17: 9/2026 | B17: ZENITH PHARMA | C17: 91206606 | D17: 438144 | F17: Accepted | H17: 09-Oct-2026
A18: 9/2026 | B18: ZENITH PHARMA | C18: 91206608 | D18: 310587.01 | F18: Accepted | H18: 09-Oct-2026
A19: 9/2026 | B19: ZENITH PHARMA | C19: 91206609 | D19: 37391.84 | F19: Accepted | H19: 09-Oct-2026
A20: 9/2026 | B20: ZENITH PHARMA | C20: 91213275 | D20: 84657.9 | F20: Pending
A21: 9/2026 | B21: ZENITH PHARMA | C21: 91213277 | D21: 592683.1 | F21: Pending
A22: 10/2026 | B22: Lanamed Trading Plc | C22: 91206748 | D22: 46729 | F22: Pending
A23: 11/2026 | B23: Kare | C23: 91205843 | D23: 389958.34 | F23: Pending
A24: 11/2026 | B24: Kare | C24: 91214870 | D24: 85423.4 | F24: Pending
A25: TOTAL | D25: =SUM(D3:D24) -> 4550592.9
